{
  "version": "6",
  "dialect": "sqlite",
  "id": "3f923ea2-925d-460a-b3bf-45434f91b901",
  "prevId": "78a0ceca-8718-4640-ba0e-0633aea0980c",
  "tables": {
    "assets": {
      "name": "assets",
      "columns": {
        "id": {
          "name": "id",
          "type": "integer",
          "primaryKey": true,
          "notNull": true,
          "autoincrement": true
        },
        "source_id": {
          "name": "source_id",
          "type": "integer",
          "primaryKey": false,
          "notNull": true,
          "autoincrement": false
        },
        "abs_path": {
          "name": "abs_path",
          "type": "text",
          "primaryKey": false,
          "notNull": true,
          "autoincrement": false
        },
        "rel_path": {
          "name": "rel_path",
          "type": "text",
          "primaryKey": false,
          "notNull": true,
          "autoincrement": false
        },
        "dir": {
          "name": "dir",
          "type": "text",
          "primaryKey": false,
          "notNull": true,
          "autoincrement": false
        },
        "name": {
          "name": "name",
          "type": "text",
          "primaryKey": false,
          "notNull": true,
          "autoincrement": false
        },
        "stem": {
          "name": "stem",
          "type": "text",
          "primaryKey": false,
          "notNull": true,
          "autoincrement": false
        },
        "ext": {
          "name": "ext",
          "type": "text",
          "primaryKey": false,
          "notNull": true,
          "autoincrement": false
        },
        "size": {
          "name": "size",
          "type": "integer",
          "primaryKey": false,
          "notNull": true,
          "autoincrement": false
        },
        "mtime": {
          "name": "mtime",
          "type": "integer",
          "primaryKey": false,
          "notNull": true,
          "autoincrement": false
        },
        "content_hash": {
          "name": "content_hash",
          "type": "text",
          "primaryKey": false,
          "notNull": true,
          "autoincrement": false
        },
        "sha1": {
          "name": "sha1",
          "type": "text",
          "primaryKey": false,
          "notNull": true,
          "autoincrement": false
        },
        "width": {
          "name": "width",
          "type": "integer",
          "primaryKey": false,
          "notNull": false,
          "autoincrement": false
        },
        "height": {
          "name": "height",
          "type": "integer",
          "primaryKey": false,
          "notNull": false,
          "autoincrement": false
        },
        "category": {
          "name": "category",
          "type": "text",
          "primaryKey": false,
          "notNull": true,
          "autoincrement": false
        },
        "phash": {
          "name": "phash",
          "type": "text",
          "primaryKey": false,
          "notNull": false,
          "autoincrement": false
        },
        "view_box": {
          "name": "view_box",
          "type": "text",
          "primaryKey": false,
          "notNull": false,
          "autoincrement": false
        },
        "paths_count": {
          "name": "paths_count",
          "type": "integer",
          "primaryKey": false,
          "notNull": false,
          "autoincrement": false
        },
        "commands_count": {
          "name": "commands_count",
          "type": "integer",
          "primaryKey": false,
          "notNull": false,
          "autoincrement": false
        },
        "has_fill": {
          "name": "has_fill",
          "type": "integer",
          "primaryKey": false,
          "notNull": false,
          "autoincrement": false
        },
        "stroke_widths": {
          "name": "stroke_widths",
          "type": "text",
          "primaryKey": false,
          "notNull": false,
          "autoincrement": false
        },
        "literal_colors": {
          "name": "literal_colors",
          "type": "text",
          "primaryKey": false,
          "notNull": false,
          "autoincrement": false
        },
        "dominant_color": {
          "name": "dominant_color",
          "type": "text",
          "primaryKey": false,
          "notNull": false,
          "autoincrement": false
        },
        "author": {
          "name": "author",
          "type": "text",
          "primaryKey": false,
          "notNull": false,
          "autoincrement": false
        },
        "clip_embedding": {
          "name": "clip_embedding",
          "type": "blob",
          "primaryKey": false,
          "notNull": false,
          "autoincrement": false
        },
        "phash_popcount": {
          "name": "phash_popcount",
          "type": "integer",
          "primaryKey": false,
          "notNull": false,
          "autoincrement": false
        },
        "raster_white_fraction": {
          "name": "raster_white_fraction",
          "type": "real",
          "primaryKey": false,
          "notNull": false,
          "autoincrement": false
        },
        "embed_status": {
          "name": "embed_status",
          "type": "text",
          "primaryKey": false,
          "notNull": false,
          "autoincrement": false
        }
      },
      "indexes": {
        "assets_abs_uq": {
          "name": "assets_abs_uq",
          "columns": [
            "abs_path"
          ],
          "isUnique": true
        },
        "assets_source_idx": {
          "name": "assets_source_idx",
          "columns": [
            "source_id"
          ],
          "isUnique": false
        },
        "assets_dir_idx": {
          "name": "assets_dir_idx",
          "columns": [
            "source_id",
            "dir"
          ],
          "isUnique": false
        },
        "assets_stem_idx": {
          "name": "assets_stem_idx",
          "columns": [
            "stem"
          ],
          "isUnique": false
        },
        "assets_hash_idx": {
          "name": "assets_hash_idx",
          "columns": [
            "content_hash"
          ],
          "isUnique": false
        },
        "assets_ext_idx": {
          "name": "assets_ext_idx",
          "columns": [
            "ext"
          ],
          "isUnique": false
        },
        "assets_phash_idx": {
          "name": "assets_phash_idx",
          "columns": [
            "ext",
            "phash"
          ],
          "isUnique": false
        }
      },
      "foreignKeys": {
        "assets_source_id_sources_id_fk": {
          "name": "assets_source_id_sources_id_fk",
          "tableFrom": "assets",
          "tableTo": "sources",
          "columnsFrom": [
            "source_id"
          ],
          "columnsTo": [
            "id"
          ],
          "onDelete": "cascade",
          "onUpdate": "no action"
        }
      },
      "compositePrimaryKeys": {},
      "uniqueConstraints": {},
      "checkConstraints": {}
    },
    "cluster_members": {
      "name": "cluster_members",
      "columns": {
        "id": {
          "name": "id",
          "type": "integer",
          "primaryKey": true,
          "notNull": true,
          "autoincrement": true
        },
        "cluster_id": {
          "name": "cluster_id",
          "type": "integer",
          "primaryKey": false,
          "notNull": true,
          "autoincrement": false
        },
        "asset_id": {
          "name": "asset_id",
          "type": "integer",
          "primaryKey": false,
          "notNull": true,
          "autoincrement": false
        },
        "role": {
          "name": "role",
          "type": "text",
          "primaryKey": false,
          "notNull": true,
          "autoincrement": false
        },
        "hamming": {
          "name": "hamming",
          "type": "integer",
          "primaryKey": false,
          "notNull": false,
          "autoincrement": false
        }
      },
      "indexes": {
        "cluster_members_cluster_idx": {
          "name": "cluster_members_cluster_idx",
          "columns": [
            "cluster_id"
          ],
          "isUnique": false
        },
        "cluster_members_asset_idx": {
          "name": "cluster_members_asset_idx",
          "columns": [
            "asset_id"
          ],
          "isUnique": false
        }
      },
      "foreignKeys": {
        "cluster_members_cluster_id_clusters_id_fk": {
          "name": "cluster_members_cluster_id_clusters_id_fk",
          "tableFrom": "cluster_members",
          "tableTo": "clusters",
          "columnsFrom": [
            "cluster_id"
          ],
          "columnsTo": [
            "id"
          ],
          "onDelete": "cascade",
          "onUpdate": "no action"
        },
        "cluster_members_asset_id_assets_id_fk": {
          "name": "cluster_members_asset_id_assets_id_fk",
          "tableFrom": "cluster_members",
          "tableTo": "assets",
          "columnsFrom": [
            "asset_id"
          ],
          "columnsTo": [
            "id"
          ],
          "onDelete": "cascade",
          "onUpdate": "no action"
        }
      },
      "compositePrimaryKeys": {},
      "uniqueConstraints": {},
      "checkConstraints": {}
    },
    "clusters": {
      "name": "clusters",
      "columns": {
        "id": {
          "name": "id",
          "type": "integer",
          "primaryKey": true,
          "notNull": true,
          "autoincrement": true
        },
        "source_id": {
          "name": "source_id",
          "type": "integer",
          "primaryKey": false,
          "notNull": true,
          "autoincrement": false
        },
        "kind": {
          "name": "kind",
          "type": "text",
          "primaryKey": false,
          "notNull": true,
          "autoincrement": false
        },
        "key": {
          "name": "key",
          "type": "text",
          "primaryKey": false,
          "notNull": true,
          "autoincrement": false
        },
        "size": {
          "name": "size",
          "type": "integer",
          "primaryKey": false,
          "notNull": true,
          "autoincrement": false
        }
      },
      "indexes": {
        "clusters_source_kind_key_uq": {
          "name": "clusters_source_kind_key_uq",
          "columns": [
            "source_id",
            "kind",
            "key"
          ],
          "isUnique": true
        },
        "clusters_source_kind_idx": {
          "name": "clusters_source_kind_idx",
          "columns": [
            "source_id",
            "kind"
          ],
          "isUnique": false
        }
      },
      "foreignKeys": {
        "clusters_source_id_sources_id_fk": {
          "name": "clusters_source_id_sources_id_fk",
          "tableFrom": "clusters",
          "tableTo": "sources",
          "columnsFrom": [
            "source_id"
          ],
          "columnsTo": [
            "id"
          ],
          "onDelete": "cascade",
          "onUpdate": "no action"
        }
      },
      "compositePrimaryKeys": {},
      "uniqueConstraints": {},
      "checkConstraints": {}
    },
    "dispatch_jobs": {
      "name": "dispatch_jobs",
      "columns": {
        "id": {
          "name": "id",
          "type": "text",
          "primaryKey": true,
          "notNull": true,
          "autoincrement": false
        },
        "source_id": {
          "name": "source_id",
          "type": "integer",
          "primaryKey": false,
          "notNull": true,
          "autoincrement": false
        },
        "plan_id": {
          "name": "plan_id",
          "type": "text",
          "primaryKey": false,
          "notNull": true,
          "autoincrement": false
        },
        "harness": {
          "name": "harness",
          "type": "text",
          "primaryKey": false,
          "notNull": true,
          "autoincrement": false
        },
        "mode": {
          "name": "mode",
          "type": "text",
          "primaryKey": false,
          "notNull": true,
          "autoincrement": false
        },
        "pid": {
          "name": "pid",
          "type": "integer",
          "primaryKey": false,
          "notNull": false,
          "autoincrement": false
        },
        "pid_started_at_ms": {
          "name": "pid_started_at_ms",
          "type": "integer",
          "primaryKey": false,
          "notNull": false,
          "autoincrement": false
        },
        "token": {
          "name": "token",
          "type": "text",
          "primaryKey": false,
          "notNull": true,
          "autoincrement": false
        },
        "status": {
          "name": "status",
          "type": "text",
          "primaryKey": false,
          "notNull": true,
          "autoincrement": false
        },
        "created_at": {
          "name": "created_at",
          "type": "text",
          "primaryKey": false,
          "notNull": true,
          "autoincrement": false,
          "default": "CURRENT_TIMESTAMP"
        },
        "ended_at": {
          "name": "ended_at",
          "type": "text",
          "primaryKey": false,
          "notNull": false,
          "autoincrement": false
        }
      },
      "indexes": {
        "dispatch_jobs_source_idx": {
          "name": "dispatch_jobs_source_idx",
          "columns": [
            "source_id"
          ],
          "isUnique": false
        },
        "dispatch_jobs_active_uq": {
          "name": "dispatch_jobs_active_uq",
          "columns": [
            "source_id"
          ],
          "isUnique": true,
          "where": "status IN ('pending', 'running')"
        }
      },
      "foreignKeys": {
        "dispatch_jobs_source_id_sources_id_fk": {
          "name": "dispatch_jobs_source_id_sources_id_fk",
          "tableFrom": "dispatch_jobs",
          "tableTo": "sources",
          "columnsFrom": [
            "source_id"
          ],
          "columnsTo": [
            "id"
          ],
          "onDelete": "cascade",
          "onUpdate": "no action"
        }
      },
      "compositePrimaryKeys": {},
      "uniqueConstraints": {},
      "checkConstraints": {}
    },
    "index_runs": {
      "name": "index_runs",
      "columns": {
        "id": {
          "name": "id",
          "type": "integer",
          "primaryKey": true,
          "notNull": true,
          "autoincrement": true
        },
        "source_id": {
          "name": "source_id",
          "type": "integer",
          "primaryKey": false,
          "notNull": true,
          "autoincrement": false
        },
        "pid": {
          "name": "pid",
          "type": "integer",
          "primaryKey": false,
          "notNull": true,
          "autoincrement": false
        },
        "pid_started_at_ms": {
          "name": "pid_started_at_ms",
          "type": "integer",
          "primaryKey": false,
          "notNull": true,
          "autoincrement": false
        },
        "status": {
          "name": "status",
          "type": "text",
          "primaryKey": false,
          "notNull": true,
          "autoincrement": false
        },
        "error": {
          "name": "error",
          "type": "text",
          "primaryKey": false,
          "notNull": false,
          "autoincrement": false
        },
        "started_at": {
          "name": "started_at",
          "type": "text",
          "primaryKey": false,
          "notNull": true,
          "autoincrement": false,
          "default": "CURRENT_TIMESTAMP"
        },
        "ended_at": {
          "name": "ended_at",
          "type": "text",
          "primaryKey": false,
          "notNull": false,
          "autoincrement": false
        }
      },
      "indexes": {
        "index_runs_source_idx": {
          "name": "index_runs_source_idx",
          "columns": [
            "source_id"
          ],
          "isUnique": false
        },
        "index_runs_active_uq": {
          "name": "index_runs_active_uq",
          "columns": [
            "source_id"
          ],
          "isUnique": true,
          "where": "status = 'running'"
        }
      },
      "foreignKeys": {
        "index_runs_source_id_sources_id_fk": {
          "name": "index_runs_source_id_sources_id_fk",
          "tableFrom": "index_runs",
          "tableTo": "sources",
          "columnsFrom": [
            "source_id"
          ],
          "columnsTo": [
            "id"
          ],
          "onDelete": "cascade",
          "onUpdate": "no action"
        }
      },
      "compositePrimaryKeys": {},
      "uniqueConstraints": {},
      "checkConstraints": {}
    },
    "sources": {
      "name": "sources",
      "columns": {
        "id": {
          "name": "id",
          "type": "integer",
          "primaryKey": true,
          "notNull": true,
          "autoincrement": true
        },
        "root": {
          "name": "root",
          "type": "text",
          "primaryKey": false,
          "notNull": true,
          "autoincrement": false
        },
        "label": {
          "name": "label",
          "type": "text",
          "primaryKey": false,
          "notNull": true,
          "autoincrement": false
        },
        "created_at": {
          "name": "created_at",
          "type": "text",
          "primaryKey": false,
          "notNull": true,
          "autoincrement": false,
          "default": "CURRENT_TIMESTAMP"
        },
        "last_indexed_at": {
          "name": "last_indexed_at",
          "type": "text",
          "primaryKey": false,
          "notNull": false,
          "autoincrement": false
        }
      },
      "indexes": {
        "sources_root_uq": {
          "name": "sources_root_uq",
          "columns": [
            "root"
          ],
          "isUnique": true
        }
      },
      "foreignKeys": {},
      "compositePrimaryKeys": {},
      "uniqueConstraints": {},
      "checkConstraints": {}
    },
    "usages": {
      "name": "usages",
      "columns": {
        "id": {
          "name": "id",
          "type": "integer",
          "primaryKey": true,
          "notNull": true,
          "autoincrement": true
        },
        "asset_id": {
          "name": "asset_id",
          "type": "integer",
          "primaryKey": false,
          "notNull": true,
          "autoincrement": false
        },
        "source_id": {
          "name": "source_id",
          "type": "integer",
          "primaryKey": false,
          "notNull": true,
          "autoincrement": false
        },
        "rel_path": {
          "name": "rel_path",
          "type": "text",
          "primaryKey": false,
          "notNull": true,
          "autoincrement": false
        },
        "abs_path": {
          "name": "abs_path",
          "type": "text",
          "primaryKey": false,
          "notNull": true,
          "autoincrement": false,
          "default": "''"
        },
        "line": {
          "name": "line",
          "type": "integer",
          "primaryKey": false,
          "notNull": true,
          "autoincrement": false
        },
        "snippet": {
          "name": "snippet",
          "type": "text",
          "primaryKey": false,
          "notNull": true,
          "autoincrement": false
        },
        "commented": {
          "name": "commented",
          "type": "integer",
          "primaryKey": false,
          "notNull": true,
          "autoincrement": false,
          "default": false
        }
      },
      "indexes": {
        "usages_asset_idx": {
          "name": "usages_asset_idx",
          "columns": [
            "asset_id"
          ],
          "isUnique": false
        },
        "usages_source_idx": {
          "name": "usages_source_idx",
          "columns": [
            "source_id"
          ],
          "isUnique": false
        }
      },
      "foreignKeys": {
        "usages_asset_id_assets_id_fk": {
          "name": "usages_asset_id_assets_id_fk",
          "tableFrom": "usages",
          "tableTo": "assets",
          "columnsFrom": [
            "asset_id"
          ],
          "columnsTo": [
            "id"
          ],
          "onDelete": "cascade",
          "onUpdate": "no action"
        },
        "usages_source_id_sources_id_fk": {
          "name": "usages_source_id_sources_id_fk",
          "tableFrom": "usages",
          "tableTo": "sources",
          "columnsFrom": [
            "source_id"
          ],
          "columnsTo": [
            "id"
          ],
          "onDelete": "cascade",
          "onUpdate": "no action"
        }
      },
      "compositePrimaryKeys": {},
      "uniqueConstraints": {},
      "checkConstraints": {}
    }
  },
  "views": {},
  "enums": {},
  "_meta": {
    "schemas": {},
    "tables": {},
    "columns": {}
  },
  "internal": {
    "indexes": {}
  }
}